lad/__init__.py
lad/lad.py
lad/lad_convert.py
lad/data/scsi_disk_devices.txt
linux_allocated-0.1.0.dist-info/LICENSE
linux_allocated-0.1.0.dist-info/METADATA
linux_allocated-0.1.0.dist-info/WHEEL
linux_allocated-0.1.0.dist-info/top_level.txt
linux_allocated-0.1.0.dist-info/RECORD
