Metadata-Version: 2.1
Name: linux-allocated
Version: 0.1.0
Summary: Linux Allocated Devices for Python
Home-page: https://github.com/svidovich/lad
Author: svidovich
Author-email: samuel.vidovich@gmail.com
License: MIT
Platform: UNKNOWN
